lattice/__init__.py
lattice/__init__.pyi
lattice/__pycache__/__init__.cpython-312.pyc
lattice/_native.cpython-312-darwin.so
lattice_lang-0.2.1.dist-info/METADATA
lattice_lang-0.2.1.dist-info/WHEEL
lattice_lang-0.2.1.dist-info/RECORD
