Metadata-Version: 2.4
Name: lattice-lang
Version: 0.2.1
Classifier: Programming Language :: Rust
Classifier: Programming Language :: Python :: Implementation :: CPython
Classifier: Programming Language :: Python :: Implementation :: PyPy
Summary: Python bindings for the Lattice language runtime
Requires-Python: >=3.8
